fortdepend/__init__.py
fortdepend/__main__.py
fortdepend/fort_depend.py
fortdepend/graph.py
fortdepend/preprocessor.py
fortdepend/smartopen.py
fortdepend/units.py
fortdepend-2.3.2.dist-info/LICENCE
fortdepend-2.3.2.dist-info/METADATA
fortdepend-2.3.2.dist-info/WHEEL
fortdepend-2.3.2.dist-info/entry_points.txt
fortdepend-2.3.2.dist-info/top_level.txt
fortdepend-2.3.2.dist-info/RECORD
