Metadata-Version: 2.1
Name: fortdepend
Version: 2.3.2
Summary: Automatically generate Fortran dependencies
Author-email: Peter Hill <peter.hill@york.ac.uk>
License: MIT
Project-URL: Source, https://github.com/ZedThree/fort_depend.py
Project-URL: Tracker, https://github.com/ZedThree/fort_depend.py/issues
Keywords: build,dependencies,fortran
Classifier: Development Status :: 5 - Production/Stable
Classifier: License :: OSI Approved :: MIT License
Classifier: Programming Language :: Python :: 3
Classifier: Programming Language :: Python :: 3.8
Classifier: Programming Language :: Python :: 3.9
Classifier: Programming Language :: Python :: 3.10
Classifier: Programming Language :: Python :: 3.11
Classifier: Programming Language :: Fortran
Requires-Python: >=3.8
License-File: LICENCE
Requires-Dist: colorama (>=0.3.9)
Requires-Dist: pcpp (>=1.1.0)
Provides-Extra: docs
Requires-Dist: sphinx (>=1.4) ; extra == 'docs'
Requires-Dist: sphinx-argparse (>=0.2.3) ; extra == 'docs'
Provides-Extra: tests
Requires-Dist: pytest (>=3.3.0) ; extra == 'tests'
